iostypingsound/audio_extractor.py
iostypingsound/ios_keys.py
iostypingsound/main.py
iostypingsound/process_manager.py
iostypingsound/root.py
iostypingsound/setup/ios-video-recording.mp4
iostypingsound-2.2.0.dist-info/LICENSE
iostypingsound-2.2.0.dist-info/METADATA
iostypingsound-2.2.0.dist-info/WHEEL
iostypingsound-2.2.0.dist-info/entry_points.txt
iostypingsound-2.2.0.dist-info/top_level.txt
iostypingsound-2.2.0.dist-info/RECORD
