Metadata-Version: 2.1
Name: iostypingsound
Version: 2.2.0
Summary: Adds the iOS Typing Sound to your system
Author: Nathan Fiscaletti
Author-email: Nathan Fiscaletti <nate.fiscaletti@gmail.com>
Project-URL: Homepage, https://github.com/nathan-fiscaletti/iostypingsound
Classifier: Programming Language :: Python :: 3
Classifier: License :: OSI Approved :: MIT License
Classifier: Operating System :: OS Independent
Requires-Python: >=3.7
License-File: LICENSE
Requires-Dist: pygame
Requires-Dist: pynput
Requires-Dist: psutil
Requires-Dist: imageio-ffmpeg
